xarray_jax/__init__.py
xarray_jax/custom_types.py
xarray_jax/register_pytrees.py
xarray_jax/tests/__init__.py
xarray_jax/tests/strategies.py
xarray_jax/tests/test_readme_examples.py
xarray_jax/tests/test_types.py
xarray_jax-0.0.5.dist-info/LICENSE
xarray_jax-0.0.5.dist-info/METADATA
xarray_jax-0.0.5.dist-info/WHEEL
xarray_jax-0.0.5.dist-info/RECORD
