Metadata-Version: 2.1
Name: xarray-jax
Version: 0.0.5
Summary: 
Author: Allen Wang
Author-email: allenw@mit.edu
Requires-Python: >=3.10,<4.0
Classifier: Programming Language :: Python :: 3
Classifier: Programming Language :: Python :: 3.10
Classifier: Programming Language :: Python :: 3.11
Classifier: Programming Language :: Python :: 3.12
Requires-Dist: equinox (>=0.11.7,<0.12.0)
Requires-Dist: jax (>=0.4.33,<0.5.0)
Requires-Dist: xarray (>=2024.9.0,<2025.0.0)
